onsi_mc/__init__.py
onsi_mc/mc.py
onsi_mc-0.1.5.dist-info/LICENSE
onsi_mc-0.1.5.dist-info/METADATA
onsi_mc-0.1.5.dist-info/WHEEL
onsi_mc-0.1.5.dist-info/RECORD
