Metadata-Version: 2.3
Name: onsi-mc
Version: 0.1.5
Summary: A Python library for Monte Carlo N-dimensional integration
License: GNU GENERAL PUBLIC LICENSE
Keywords: monte-carlo,integration,numerical-integration,high-dimensional,scientific-computing,python-library
Author: Ali Onsi
Author-email: aonsi@alexu.edu.eg
Requires-Python: >=3.8
Classifier: License :: OSI Approved :: GNU General Public License v3 (GPLv3)
Classifier: Programming Language :: Python :: 3.8
Classifier: Programming Language :: Python :: 3.9
Classifier: Programming Language :: Python :: 3.10
Classifier: Programming Language :: Python :: 3.11
Classifier: Programming Language :: Python :: 3.12
Requires-Dist: matplotlib (>=3.0.0)
Requires-Dist: numba (>=0.56.0)
Requires-Dist: numpy (>=1.21.0)
Requires-Dist: tqdm (>=4.0.0)
